validator/__init__.py
validator/exceptions.py
validator/fields.py
validator/locale/python-validator.po
validator/locale/zh_CN/LC_MESSAGES/python-validator.mo
validator/locale/zh_CN/LC_MESSAGES/python-validator.po
validator/translation.py
validator/utils.py
validator/validator.py
python_validator-0.0.8.dist-info/LICENSE
python_validator-0.0.8.dist-info/WHEEL
python_validator-0.0.8.dist-info/METADATA
python_validator-0.0.8.dist-info/RECORD
