Metadata-Version: 2.1
Name: python-validator
Version: 0.0.8
Summary: a data validator like Django ORM
Home-page: https://github.com/ausaki/python-validator
License: MIT
Keywords: data validator
Author: ausaki
Author-email: ljm51689@gmail.com
Requires-Python: >=3.6.0
Classifier: License :: OSI Approved :: MIT License
Classifier: Programming Language :: Python :: 3
Classifier: Programming Language :: Python :: 3.6
Classifier: Programming Language :: Python :: 3.7
Classifier: Programming Language :: Python :: 3.8
Classifier: Programming Language :: Python :: 3.9
Provides-Extra: tzinfo
Requires-Dist: IPy
Requires-Dist: pytz; extra == "tzinfo"
Requires-Dist: six (>=1.15.0,<2.0.0)
Project-URL: Documentation, https://ausaki.github.io/python-validator/
Project-URL: Repository, https://github.com/ausaki/python-validator
